oshino_elasticsearch/__init__.py
oshino_elasticsearch/agent.py
oshino_elasticsearch/version.py
oshino_elasticsearch-0.1.5.dist-info/DESCRIPTION.rst
oshino_elasticsearch-0.1.5.dist-info/METADATA
oshino_elasticsearch-0.1.5.dist-info/RECORD
oshino_elasticsearch-0.1.5.dist-info/WHEEL
oshino_elasticsearch-0.1.5.dist-info/metadata.json
oshino_elasticsearch-0.1.5.dist-info/top_level.txt
