Metadata-Version: 2.0
Name: oshino-elasticsearch
Version: 0.1.5
Summary: ElasticSearch metric collector
Home-page: UNKNOWN
Author: Šarūnas Navickas
Author-email: zaibacu@gmail.com
License: UNKNOWN
Platform: UNKNOWN
Requires-Dist: oshino
